vibecore/__init__.py
vibecore/cli.py
vibecore/context.py
vibecore/flow.py
vibecore/main.py
vibecore/main.tcss
vibecore/py.typed
vibecore/settings.py
vibecore/agents/default.py
vibecore/agents/prompts.py
vibecore/agents/task.py
vibecore/auth/__init__.py
vibecore/auth/config.py
vibecore/auth/interceptor.py
vibecore/auth/manager.py
vibecore/auth/models.py
vibecore/auth/oauth_flow.py
vibecore/auth/pkce.py
vibecore/auth/storage.py
vibecore/auth/token_manager.py
vibecore/handlers/__init__.py
vibecore/handlers/stream_handler.py
vibecore/mcp/__init__.py
vibecore/mcp/manager.py
vibecore/mcp/server_wrapper.py
vibecore/models/__init__.py
vibecore/models/anthropic.py
vibecore/models/anthropic_auth.py
vibecore/prompts/common_system_prompt.txt
vibecore/session/__init__.py
vibecore/session/file_lock.py
vibecore/session/jsonl_session.py
vibecore/session/loader.py
vibecore/session/path_utils.py
vibecore/tools/__init__.py
vibecore/tools/base.py
vibecore/tools/path_validator.py
vibecore/tools/file/__init__.py
vibecore/tools/file/executor.py
vibecore/tools/file/tools.py
vibecore/tools/file/utils.py
vibecore/tools/python/__init__.py
vibecore/tools/python/helpers.py
vibecore/tools/python/manager.py
vibecore/tools/python/tools.py
vibecore/tools/python/backends/__init__.py
vibecore/tools/python/backends/terminal_backend.py
vibecore/tools/shell/__init__.py
vibecore/tools/shell/executor.py
vibecore/tools/shell/tools.py
vibecore/tools/task/__init__.py
vibecore/tools/task/executor.py
vibecore/tools/task/tools.py
vibecore/tools/todo/__init__.py
vibecore/tools/todo/manager.py
vibecore/tools/todo/models.py
vibecore/tools/todo/tools.py
vibecore/tools/webfetch/__init__.py
vibecore/tools/webfetch/executor.py
vibecore/tools/webfetch/models.py
vibecore/tools/webfetch/tools.py
vibecore/tools/websearch/__init__.py
vibecore/tools/websearch/base.py
vibecore/tools/websearch/executor.py
vibecore/tools/websearch/models.py
vibecore/tools/websearch/tools.py
vibecore/tools/websearch/ddgs/__init__.py
vibecore-0.6.4.dist-info/METADATA
vibecore-0.6.4.dist-info/WHEEL
vibecore-0.6.4.dist-info/entry_points.txt
vibecore-0.6.4.dist-info/licenses/LICENSE
vibecore-0.6.4.dist-info/RECORD
