Metadata-Version: 2.4
Name: vibecore
Version: 0.6.4
Summary: Build your own AI-powered automation tools in the terminal with this extensible agent framework
Project-URL: Homepage, https://github.com/serialx/vibecore
Project-URL: Repository, https://github.com/serialx/vibecore
Project-URL: Bug Tracker, https://github.com/serialx/vibecore/issues
Project-URL: Discussions, https://github.com/serialx/vibecore/discussions
Project-URL: Documentation, https://github.com/serialx/vibecore#readme
Author-email: Sung-jin Brian Hong <serialx@serialx.net>
License: MIT
License-File: LICENSE
Keywords: agents,ai,anthropic,assistant,automation,claude,cli,framework,gpt,mcp,model-context-protocol,openai,terminal,textual,tool-use,tui
Classifier: Development Status :: 3 - Alpha
Classifier: Environment :: Console
Classifier: Intended Audience :: Developers
Classifier: License :: OSI Approved :: MIT License
Classifier: Operating System :: OS Independent
Classifier: Programming Language :: Python :: 3
Classifier: Programming Language :: Python :: 3.11
Classifier: Programming Language :: Python :: 3.12
Classifier: Programming Language :: Python :: 3.13
Classifier: Topic :: Scientific/Engineering :: Artificial Intelligence
Classifier: Topic :: Software Development :: Libraries :: Application Frameworks
Classifier: Topic :: Software Development :: User Interfaces
Classifier: Topic :: Terminals
Classifier: Topic :: Text Processing :: Linguistic
Classifier: Typing :: Typed
Requires-Python: >=3.11
Requires-Dist: ddgs>=9.5.4
Requires-Dist: html2text>=2024.2.26
Requires-Dist: httpx>=0.24.0
Requires-Dist: litellm>=1.72.4
Requires-Dist: openai-agents[litellm]>=0.2.2
Requires-Dist: pydantic-settings>=2.10.1
Requires-Dist: textual>=4.0.0
Requires-Dist: typer>=0.14.0
